ssb_flit2/__init__.py
ssb_flit2/example.py
ssb_flit2-0.0.2.dist-info/LICENSE
ssb_flit2-0.0.2.dist-info/WHEEL
ssb_flit2-0.0.2.dist-info/METADATA
ssb_flit2-0.0.2.dist-info/RECORD
