Metadata-Version: 2.1
Name: ssb-flit2
Version: 0.0.2
Summary: Description ssb
Author: ssb
Classifier: License :: OSI Approved :: MIT License
